README.md
setup.py
arek_frel89_school.egg-info/PKG-INFO
arek_frel89_school.egg-info/SOURCES.txt
arek_frel89_school.egg-info/dependency_links.txt
arek_frel89_school.egg-info/top_level.txt
plafrel_89school/__init__.py
plafrel_89school/classroom.py
plafrel_89school/setup.py
plafrel_89school/student.py