Metadata-Version: 2.1
Name: arek-frel89-school
Version: 1.0.0
Summary: School abstraction library
Home-page: UNKNOWN
License: UNKNOWN
Platform: UNKNOWN
